{
  "generated_at": "2026-04-22T19:30:32.182Z",
  "total_articles": 4459,
  "with_fedlex_url": 4459,
  "without_fedlex_url": 0,
  "stale_articles": [],
  "no_date_articles": [],
  "url_checks": [
    {
      "ref": "CC 8",
      "url": "https://www.fedlex.admin.ch/eli/cc/24/233_245_233/fr#art_8",
      "status": "ok",
      "code": 200
    },
    {
      "ref": "CO 55",
      "url": "https://www.fedlex.admin.ch/eli/cc/27/317_321_377/fr#art_55",
      "status": "ok",
      "code": 200
    },
    {
      "ref": "CO 511",
      "url": "https://www.fedlex.admin.ch/eli/cc/27/317_321_377/fr#art_511",
      "status": "ok",
      "code": 200
    },
    {
      "ref": "CC 365",
      "url": "https://www.fedlex.admin.ch/eli/cc/24/233_245_233/fr#art_365",
      "status": "ok",
      "code": 200
    },
    {
      "ref": "CO 458",
      "url": "https://www.fedlex.admin.ch/eli/cc/27/317_321_377/fr#art_458",
      "status": "ok",
      "code": 200
    },
    {
      "ref": "LAsi 55",
      "url": "https://www.fedlex.admin.ch/eli/cc/1999/358/fr#art_55",
      "status": "ok",
      "code": 200
    },
    {
      "ref": "CO 571",
      "url": "https://www.fedlex.admin.ch/eli/cc/27/317_321_377/fr#art_571",
      "status": "ok",
      "code": 200
    },
    {
      "ref": "CC 301",
      "url": "https://www.fedlex.admin.ch/eli/cc/24/233_245_233/fr#art_301",
      "status": "ok",
      "code": 200
    },
    {
      "ref": "LAsi 25",
      "url": "https://www.fedlex.admin.ch/eli/cc/1999/358/fr#art_25",
      "status": "ok",
      "code": 200
    },
    {
      "ref": "CO 533",
      "url": "https://www.fedlex.admin.ch/eli/cc/27/317_321_377/fr#art_533",
      "status": "ok",
      "code": 200
    },
    {
      "ref": "CC 291",
      "url": "https://www.fedlex.admin.ch/eli/cc/24/233_245_233/fr#art_291",
      "status": "ok",
      "code": 200
    },
    {
      "ref": "CC 345",
      "url": "https://www.fedlex.admin.ch/eli/cc/24/233_245_233/fr#art_345",
      "status": "ok",
      "code": 200
    },
    {
      "ref": "CO 364",
      "url": "https://www.fedlex.admin.ch/eli/cc/27/317_321_377/fr#art_364",
      "status": "ok",
      "code": 200
    },
    {
      "ref": "CO 453",
      "url": "https://www.fedlex.admin.ch/eli/cc/27/317_321_377/fr#art_453",
      "status": "ok",
      "code": 200
    },
    {
      "ref": "CO 508",
      "url": "https://www.fedlex.admin.ch/eli/cc/27/317_321_377/fr#art_508",
      "status": "ok",
      "code": 200
    },
    {
      "ref": "LAsi 40",
      "url": "https://www.fedlex.admin.ch/eli/cc/1999/358/fr#art_40",
      "status": "ok",
      "code": 200
    },
    {
      "ref": "CO 360",
      "url": "https://www.fedlex.admin.ch/eli/cc/27/317_321_377/fr#art_360",
      "status": "ok",
      "code": 200
    },
    {
      "ref": "CC 322",
      "url": "https://www.fedlex.admin.ch/eli/cc/24/233_245_233/fr#art_322",
      "status": "ok",
      "code": 200
    },
    {
      "ref": "CO 401",
      "url": "https://www.fedlex.admin.ch/eli/cc/27/317_321_377/fr#art_401",
      "status": "ok",
      "code": 200
    },
    {
      "ref": "CO 459",
      "url": "https://www.fedlex.admin.ch/eli/cc/27/317_321_377/fr#art_459",
      "status": "ok",
      "code": 200
    }
  ],
  "summary": {
    "freshness": {
      "fresh": 4459,
      "stale": 0,
      "unknown": 0
    },
    "freshness_rate": "100%",
    "stale_rate": "0%",
    "broken_urls": 0,
    "url_check_sample_size": 20,
    "needs_reharvest": false
  }
}